setup.py
bug_spots.egg-info/PKG-INFO
bug_spots.egg-info/SOURCES.txt
bug_spots.egg-info/dependency_links.txt
bug_spots.egg-info/entry_points.txt
bug_spots.egg-info/requires.txt
bug_spots.egg-info/top_level.txt
bugspots/__init__.py