Metadata-Version: 1.1
Name: bug-spots
Version: 0.2.5
Summary: A Python based implementation of the bug prediction algorithm proposed by Google
Home-page: UNKNOWN
Author: Jorge Niedbalski R.
Author-email: jnr@pyrosome.org
License: BSD
Keywords: bugspot bug spots bug prediction
Platform: UNKNOWN
Classifier: Development Status :: 3 - Alpha
Classifier: Intended Audience :: Developers
Classifier: Operating System :: Unix 
